pytest_tap/__init__.py
pytest_tap/plugin.py
pytest_tap-3.5.dist-info/METADATA
pytest_tap-3.5.dist-info/WHEEL
pytest_tap-3.5.dist-info/entry_points.txt
pytest_tap-3.5.dist-info/licenses/AUTHORS
pytest_tap-3.5.dist-info/licenses/LICENSE
pytest_tap-3.5.dist-info/RECORD
