Metadata-Version: 2.4
Name: pytest-tap
Version: 3.5
Summary: Test Anything Protocol (TAP) reporting plugin for pytest
Author-email: Matt Layman <matthewlayman@gmail.com>
License: BSD
License-File: AUTHORS
License-File: LICENSE
Keywords: TAP,pytest,unittest
Classifier: Development Status :: 5 - Production/Stable
Classifier: Framework :: Pytest
Classifier: Intended Audience :: Developers
Classifier: License :: OSI Approved :: BSD License
Classifier: Operating System :: OS Independent
Classifier: Programming Language :: Python :: 3.9
Classifier: Programming Language :: Python :: 3.10
Classifier: Programming Language :: Python :: 3.11
Classifier: Programming Language :: Python :: 3.12
Classifier: Programming Language :: Python :: 3.13
Classifier: Topic :: Software Development :: Testing
Requires-Python: >=3.9
Requires-Dist: pytest>=3.0
Requires-Dist: tap-py<4.0,>=3.2
